<?xml version="1.0"?>
<includes>
  <!-- Time -->
  <include name="Furniture_TimePanel">
    <control type="image">
      <posx>-60</posx>
      <posy>0</posy>
      <width>451</width>
      <height>27</height>
      <texture>common/timepanel_mid.png</texture>
      <animation type="Conditional" condition="Skin.HasSetting(bighome)">
        <effect type="slide" end="10,-7" time="0"/>
        <effect type="zoom" start="125" end="125" time="0"/>
      </animation>
    </control>
    <control type="image">
      <description>Weather image</description>
      <posx>-45</posx>
      <posy>1</posy>
      <width>23</width>
      <height>23</height>
      <aspectratio>keep</aspectratio>
      <aligny>center</aligny>
      <texture>$INFO[Weather.Conditions]</texture>
      <animation type="Conditional" condition="Skin.HasSetting(bighome)">
        <effect type="slide" end="10,-7" time="0"/>
        <effect type="zoom" start="125" end="125" time="0"/>
      </animation>
    </control>
    <control type="label">
      <posx>370</posx>
      <posy>3</posy>
      <width>400</width>
      <font>Font_Time</font>
      <align>right</align>
      <include>Colour_WhiteAlpha80</include>
      <visible>!Skin.HasSetting(bighome)</visible>
      <label>[COLOR FFe5e5e5][UPPERCASE]$INFO[System.Date][/UPPERCASE]  |  [/COLOR][COLOR FFcdcdcd]$INFO[System.Time][/COLOR]</label>
    </control>
    <control type="label">
      <posx>-20</posx>
      <posy>3</posy>
      <width>400</width>
      <font>Font_Time</font>
      <align>left</align>
      <include>Colour_WhiteAlpha80</include>
      <visible>!Skin.HasSetting(bighome)</visible>
      <label>$INFO[Window(Weather).Property(Current.Temperature)]$INFO[System.TemperatureUnits]</label>
    </control>
    <control type="label">
      <posx>370</posx>
      <posy>-4</posy>
      <width>600</width>
      <font>Font_BigHome</font>
      <align>right</align>
      <include>Colour_WhiteAlpha80</include>
      <visible>Skin.HasSetting(bighome)</visible>
      <label>[COLOR FFe5e5e5][UPPERCASE]$INFO[System.Date][/UPPERCASE]  |  [/COLOR][COLOR FFcdcdcd]$INFO[System.Time][/COLOR]</label>
    </control>
    <control type="label">
      <posx>-15</posx>
      <posy>-4</posy>
      <width>600</width>
      <font>Font_BigHome</font>
      <align>left</align>
      <include>Colour_WhiteAlpha80</include>
      <visible>Skin.HasSetting(bighome)</visible>
      <label>$INFO[Window(Weather).Property(Current.Temperature)]$INFO[System.TemperatureUnits]</label>
    </control>
  </include>
  <include name="Furniture_TimePanelHigh">
    <control type="image">
      <posx>-60</posx>
      <posy>0</posy>
      <width>451</width>
      <height>27</height>
      <texture flipy="true">common/timepanel_mid.png</texture>
      <animation type="Conditional" condition="Skin.HasSetting(bighome)">
        <effect type="slide" end="-30,0" time="0"/>
        <effect type="zoom" end="120" time="0"/>
      </animation>
    </control>
    <control type="image">
      <description>Weather image</description>
      <animation type="Conditional" condition="Skin.HasSetting(bighome)">
        <effect type="slide" end="-30,2" time="0"/>
        <effect type="zoom" end="120" time="0"/>
      </animation>
      <posx>-45</posx>
      <posy>1</posy>
      <width>23</width>
      <height>23</height>
      <aspectratio>keep</aspectratio>
      <aligny>center</aligny>
      <texture>$INFO[Weather.Conditions]</texture>
    </control>
    <control type="label">
      <posx>370</posx>
      <posy>3</posy>
      <width>400</width>
      <font>Font_Time</font>
      <align>right</align>
      <include>Colour_WhiteAlpha80</include>
      <visible>!Skin.HasSetting(bighome)</visible>
      <label>[COLOR FFe5e5e5][UPPERCASE]$INFO[System.Date][/UPPERCASE]  |  [/COLOR][COLOR FFcdcdcd]$INFO[System.Time][/COLOR]</label>
    </control>
    <control type="label">
      <posx>-20</posx>
      <posy>3</posy>
      <width>400</width>
      <font>Font_Time</font>
      <align>left</align>
      <include>Colour_WhiteAlpha80</include>
      <visible>!Skin.HasSetting(bighome)</visible>
      <label>$INFO[Window(Weather).Property(Current.Temperature)]$INFO[System.TemperatureUnits]</label>
    </control>
    <control type="label">
      <posx>370</posx>
      <posy>3</posy>
      <width>600</width>
      <font>Font_BigHome</font>
      <align>right</align>
      <include>Colour_WhiteAlpha80</include>
      <visible>Skin.HasSetting(bighome)</visible>
      <label>[COLOR FFe5e5e5][UPPERCASE]$INFO[System.Date][/UPPERCASE]  |  [/COLOR][COLOR FFcdcdcd]$INFO[System.Time][/COLOR]</label>
    </control>
    <control type="label">
      <posx>-40</posx>
      <posy>3</posy>
      <width>400</width>
      <font>Font_BigHome</font>
      <align>left</align>
      <include>Colour_WhiteAlpha80</include>
      <visible>Skin.HasSetting(bighome)</visible>
      <label>$INFO[Window(Weather).Property(Current.Temperature)]$INFO[System.TemperatureUnits]</label>
    </control>
  </include>
  <include name="Furniture_Time">
    <control type="group">
      <posx>900</posx>
      <posy>316</posy>
      <width>451</width>
      <height>27</height>
      <visible>!Skin.HasSetting(highertime) + Window.IsActive(Home) + !Control.IsVisible(553) + !Control.IsVisible(51) + !Control.IsVisible(55) + !Control.IsVisible(52) + !Control.IsVisible(552) + !Control.IsVisible(57) + !Control.IsVisible(50) + !Control.IsVisible(53) + !Control.IsVisible(550) + !Control.IsVisible(551) + !Control.IsVisible(560)</visible>
      <animation effect="slide" start="0,0" end="0,225" time="400" tween="cubic" easing="inout" condition="Skin.HasSetting(lowermainmenu)">Conditional</animation>
      <include>Animation_OpenCloseZoom</include>
      <include>Furniture_TimePanel</include>
    </control>
    <control type="group">
      <posx>900</posx>
      <posy>0</posy>
      <width>451</width>
      <height>27</height>
      <animation effect="slide" start="0,0" end="0,-37" time="200" condition="[Control.IsVisible(57) + Control.HasFocus(70197)]">Conditional</animation>
      <visible>[Skin.HasSetting(highertime) + Window.IsActive(Home)] | Window.IsActive(FileManager) | [[Control.IsVisible(553) | Control.IsVisible(50) | Control.IsVisible(55) | Control.IsVisible(52) | Control.IsVisible(556) |  Control.IsVisible(556) | Control.IsVisible(552) | Control.IsVisible(57) | Control.IsVisible(550) | Control.IsVisible(551) | Control.IsVisible(51) | Control.IsVisible(53)] + !Window.IsVisible(112) + !Window.IsVisible(133)]</visible>
      <include>Furniture_TimePanelHigh</include>
      <animation type="WindowOpen" reversible="false" condition="Window.Previous(Startup)">
        <effect type="zoom" start="180" end="100" center="640,360" time="2500" tween="cubic" easing="out"/>
        <effect type="fade" start="0" end="100" time="2000"/>
      </animation>
      <animation type="WindowOpen" reversible="false" condition="!Window.Previous(Startup)">
        <effect type="zoom" start="150" end="100" center="640,360" time="900" tween="cubic" easing="out"/>
        <effect type="fade" start="0" end="100" time="900"/>
      </animation>
      <animation type="WindowClose" reversible="false">
        <effect type="fade" start="100" end="0" time="300"/>
        <effect type="zoom" start="100" end="130" center="640,360" time="300" tween="cubic" easing="in"/>
      </animation>
    </control>
    <control type="group">
      <posx>900</posx>
      <posy>45</posy>
      <width>451</width>
      <height>27</height>
      <visible>!Window.IsActive(FileManager) + !Window.IsActive(Home) + !Control.IsVisible(553) + !Control.IsVisible(51) + !Control.IsVisible(52) + !Control.IsVisible(55) + !Control.IsVisible(552) + !Control.IsVisible(57) + !Control.IsVisible(50) + !Control.IsVisible(550) + !Control.IsVisible(551) + !Control.IsVisible(53) + !Control.IsVisible(556) + !Control.IsVisible(557) + !Control.isVisible(560) + !Control.IsVisible(54)</visible>
      <include>Furniture_TimePanel</include>
      <include>Animation_OpenCloseZoom</include>
    </control>
  </include>
  <!-- RSS Feeds-->
  <include name="Furniture_RSS">
    <control type="group">
      <posx>-400</posx>
      <posy>0</posy>
      <width>1280</width>
      <height>57</height>
      <visible>!Control.IsVisible(560) + !Control.IsVisible(54) + !Player.HasMedia</visible>
      <animation effect="slide" start="0,0" end="0,-37" time="300" condition="[Control.IsVisible(53) + !Control.HasFocus(53) + !Control.HasFocus(71)] | [Control.IsVisible(57) + Control.HasFocus(70197)] | Control.IsVisible(7777)">Conditional</animation>
      <include>Animation_WidgetZoom</include>
      <control type="image">
        <posx>0</posx>
        <posy>0</posy>
        <width>1240</width>
        <height>27</height>
        <texture>common/rssbar_fs.png</texture>
        <include>Animation_CommonFade</include>
        <animation type="Conditional" condition="Skin.HasSetting(bighome)">
          <effect type="slide" start="-472,0" end="-472,0" time="0"/>
          <effect type="zoom" start="116" end="116" time="0"/>
        </animation>
      </control>
      <control type="rss" id="1">
        <description>My First RSS control</description>
        <posx>-70</posx>
        <posy>3</posy>
        <width>1280</width>
        <visible>![Player.HasAudio | Skin.HasSetting(bighome)]</visible>
        <font>Font_Time</font>
        <urlset>1</urlset>
        <include>Colour_RSSLight</include>
        <include>Animation_CommonFade</include>
      </control>
      <control type="rss" id="1">
        <posx>-170</posx>
        <posy>3</posy>
        <width>1098</width>
        <font>Font_BigRSS</font>
        <include>Colour_RSSLight</include>
        <urlset>1</urlset>
        <include>Animation_CommonFade</include>
        <visible>!Player.HasAudio + Skin.HasSetting(bighome)</visible>
      </control>
    </control>
  </include>
  <!-- Media windows -->
  <include name="ShowcaseFloorNight">
    <texture>showcase/showcase_floor.png</texture>
  </include>
  <include name="ShowcaseFloorLight">
    <texture>showcase/lite/showcase_floor.png</texture>
  </include>
  <include name="ListFloorNight">
    <texture>list/list_floor.png</texture>
  </include>
  <include name="ListFloorLight">
    <texture>list/lite/list_floor.png</texture>
  </include>
  <include name="Furniture_MediaPanel">
    <control type="image">
      <include>FullscreenDimensions</include>
      <texture>list/list_filter.png</texture>
      <colordiffuse>d0FFFFFF</colordiffuse>
      <visible>Control.IsVisible(50)| Control.IsVisible(551)</visible>
    </control>
    <control type="image">
      <animation effect="slide" end="0,25" time="400" easing="inout" tween="cubic" condition="Control.IsVisible(57) + [!Skin.HasSetting(showcaseinfolines) | Container.Content(years) | Container.Content(genres)]">Conditional</animation>
      <posx>0</posx>
      <posy>335</posy>
      <width>1280</width>
      <height>405</height>
      <include condition="!Skin.HasSetting(darkfloor)">ShowcaseFloorLight</include>
      <include condition="Skin.HasSetting(darkfloor)">ShowcaseFloorNight</include>
      <visible>Control.IsVisible(57) | Control.IsVisible(52) | Control.IsVisible(53) | Control.IsVisible(500) | Control.IsVisible(501) | Control.IsVisible(502) | Control.IsVisible(552)</visible>
      <!--ADDED WALL FLOOR-->
      <include>Animation_CommonFade</include>
      <include>Animation_HideShowcase</include>
      <include>Animation_HideMultiplex</include>
    </control>
    <control type="image">
      <animation effect="slide" end="0,25" time="400" easing="inout" tween="cubic" condition="Control.IsVisible(57) + [!Skin.HasSetting(showcaseinfolines) | Container.Content(years) | Container.Content(genres)]">Conditional</animation>
      <posx>144</posx>
      <posy>603</posy>
      <width>993</width>
      <height>137</height>
      <include condition="!Skin.HasSetting(darkfloor)">ShowcaseSpotLight</include>
      <include condition="Skin.HasSetting(darkfloor)">ShowcaseSpotNight</include>
      <include>Animation_CommonFade</include>
      <include>Animation_HideShowcase</include>
      <include>Animation_HideMultiplex</include>
      <visible>Control.IsVisible(57) | Control.IsVisible(52) | Control.IsVisible(53) | Control.IsVisible(552) | Control.IsVisible(50)</visible>
    </control>
    <control type="image">
      <posx>0</posx>
      <posy>65</posy>
      <width>1280</width>
      <height>675</height>
      <include condition="!Skin.HasSetting(darkfloor)">ShowcaseFloorLight</include>
      <include condition="Skin.HasSetting(darkfloor)">ShowcaseFloorNight</include>
      <visible>Control.IsVisible(55)</visible>
      <!--ADDED WALL FLOOR-->
      <include>Animation_CommonFade</include>
      <include>Animation_HideShowcase</include>
      <include>Animation_HideMultiplex</include>
    </control>
    <control type="image">
      <posx>144</posx>
      <posy>510</posy>
      <width>993</width>
      <height>207</height>
      <include condition="!Skin.HasSetting(darkfloor)">ShowcaseSpotLight</include>
      <include condition="Skin.HasSetting(darkfloor)">ShowcaseSpotNight</include>
      <include>Animation_CommonFade</include>
      <include>Animation_HideShowcase</include>
      <include>Animation_HideMultiplex</include>
      <visible>Control.IsVisible(55)</visible>
    </control>
    <!--	<control type="image">
			<posx>144</posx>
			<posy>583</posy>
			<width>993</width>
			<height>137</height>
			<include>ShowcaseSpotLight</include>
			<include>Animation_CommonFade</include>
			<include>Animation_HideShowcase</include>
			<visible>Control.IsVisible(50)</visible>
		</control>-->
    <control type="image">
      <animation effect="slide" end="0,25" time="400" easing="inout" tween="cubic" condition="Control.IsVisible(57) + [!Skin.HasSetting(showcaseinfolines) | Container.Content(genres)]">Conditional</animation>
      <posx>0</posx>
      <posy>335</posy>
      <width>1280</width>
      <height>405</height>
      <include condition="!Skin.HasSetting(darkfloor)">ListFloorLight</include>
      <include condition="Skin.HasSetting(darkfloor)">ListFloorNight</include>
      <visible>Control.IsVisible(50)</visible>
      <include>Animation_CommonFade</include>
      <include>Animation_HideShowcase</include>
      <include>Animation_HideMultiplex</include>
    </control>
    <control type="image">
      <!-- lowlist-->
      <animation effect="slide" end="0,30" time="400" easing="inout" tween="cubic" condition="Control.IsVisible(57) + [!Skin.HasSetting(showcaseinfolines) | Container.Content(genres)]">Conditional</animation>
      <posx>140</posx>
      <posy>503</posy>
      <width>993</width>
      <height>325</height>
      <texture>showcase/showcase_spot.png</texture>
      <include>Animation_CommonFade</include>
      <include>Animation_HideShowcase</include>
      <include>Animation_HighListSlide</include>
      <visible>Control.IsVisible(551)</visible>
      <animation effect="fade" start="100" end="60" time="50" condition="!Skin.HasSetting(listpanelthin)">Conditional</animation>
      <animation effect="fade" start="100" end="10" time="50" condition="Skin.HasSetting(listpanelthin)">Conditional</animation>
    </control>
    <control type="image">
      <posx>0</posx>
      <posy>0</posy>
      <width>464</width>
      <height>720</height>
      <texture>showcase/showcase_vignette.png</texture>
      <visible>[[Control.IsVisible(55) | Control.IsVisible(57) | Control.IsVisible(50) | Control.IsVisible(551) | Control.IsVisible(52) | Control.IsVisible(55) | Control.IsVisible(552)] + ![Control.HasFocus(197) | Control.HasFocus(70197)]] + ![Window.IsActive(musicplaylist) | Window.IsActive(musicfiles) | Window.IsActive(musiclibrary)]</visible>
      <animation type="Visible">
        <effect type="fade" start="0" end="100" time="400" easing="inout" tween="cubic"/>
        <effect type="slide" start="-464,0" end="0,0" time="400" easing="inout" tween="cubic"/>
      </animation>
      <animation type="Hidden">
        <effect type="fade" start="100" end="0" time="400" easing="inout" tween="cubic"/>
        <effect type="slide" start="0,0" end="-464,0" time="400" easing="inout" tween="cubic"/>
      </animation>
      <animation type="WindowOpen">
        <effect type="fade" start="0" end="100" time="400" easing="inout" tween="cubic"/>
        <effect type="slide" start="-464,0" end="0,0" time="400" easing="inout" tween="cubic"/>
      </animation>
      <animation type="WindowClose">
        <effect type="fade" start="100" end="0" time="400" easing="inout" tween="cubic"/>
        <effect type="slide" start="0,0" end="-464,0" time="400" easing="inout" tween="cubic"/>
      </animation>
    </control>
    <control type="image">
      <posx>816</posx>
      <posy>0</posy>
      <width>464</width>
      <height>720</height>
      <texture flipx="true">showcase/showcase_vignette.png</texture>
      <visible>[[Control.IsVisible(55) | Control.IsVisible(57) | Control.IsVisible(50)| Control.IsVisible(551) |  Control.IsVisible(52) | Control.IsVisible(55) | Control.IsVisible(552)] + ![Control.HasFocus(197) | Control.HasFocus(70197)]] + ![Window.IsActive(musicplaylist) | Window.IsActive(musicfiles) | Window.IsActive(musiclibrary)]</visible>
      <animation type="Visible">
        <effect type="fade" start="0" end="100" time="400" easing="inout" tween="cubic"/>
        <effect type="slide" start="464,0" end="0,0" time="400" easing="inout" tween="cubic"/>
      </animation>
      <animation type="Hidden">
        <effect type="fade" start="100" end="0" time="400" easing="inout" tween="cubic"/>
        <effect type="slide" start="0,0" end="464,0" time="400" easing="inout" tween="cubic"/>
      </animation>
      <animation type="WindowOpen">
        <effect type="fade" start="0" end="100" time="400" easing="inout" tween="cubic"/>
        <effect type="slide" start="464,0" end="0,0" time="400" easing="inout" tween="cubic"/>
      </animation>
      <animation type="WindowClose">
        <effect type="fade" start="100" end="0" time="400" easing="inout" tween="cubic"/>
        <effect type="slide" start="0,0" end="464,0" time="400" easing="inout" tween="cubic"/>
      </animation>
    </control>
  </include>
  <include name="Furniture_FloorText">
    <control type="group">
      <visible>[Control.IsVisible(52) + !Window.IsActive(musiclibrary)] | Control.IsVisible(552) | Control.IsVisible(57) | Control.IsVisible(53) | Control.IsVisible(55)</visible>
      <include>Animation_HideMultiplex</include>
      <include>Animation_HideShowcase</include>
      <include>Animation_OpenCloseZoom</include>
      <animation type="Conditional" condition="Control.IsVisible(7777) + Control.IsVisible(57) + ![[Skin.HasSetting(flattenshowcasemovies) + Skin.HasSetting(videomovies)] | [Skin.HasSetting(flattenshowcasetvshows) + Container.Content(tvshows)] | [Skin.HasSetting(flattenshowcaseseasons) + Container.Content(seasons)] | [Skin.HasSetting(flattenshowcaseepisodes) + Container.Content(episodes)] | [!Window.IsActive(videolibrary) + !Window.IsActive(videofiles) + Skin.HasSetting(flattenshowcasemusic)]] + Skin.HasSetting(mediamenuslide)">
        <effect type="slide" end="-70,0" time="400" easing="out" tween="cubic"/>
      </animation>
      <control type="label">
        <label>[B][UPPERCASE]$INFO[ListItem.Label][/UPPERCASE][/B]</label>
        <include>FloorTextMainLabel</include>
        <visible>Container.Content(movies)</visible>
      </control>
      <control type="label">
        <label>[B][UPPERCASE]$INFO[ListItem.Label][/UPPERCASE][/B]</label>
        <include>FloorTextMainLabelWide</include>
        <visible>!Container.Content(episodes) +  !Container.Content(movies)</visible>
      </control>
      <control type="label">
        <label>[UPPERCASE]$INFO[ListItem.Season].$INFO[ListItem.Episode]: $INFO[ListItem.Title][/UPPERCASE]</label>
        <include>FloorTextMainLabel</include>
        <visible>Container.Content(episodes)</visible>
      </control>
      <control type="label">
        <label>[B][UPPERCASE]$INFO[Container.NumItems] $LOCALIZE[31005][/UPPERCASE][/B]</label>
        <include>FloorTextLabel</include>
        <posx>340</posx>
        <posy>693</posy>
        <width>600</width>
        <font>Font_FloorTextMainLabel</font>
        <include condition="!Skin.HasSetting(darkfloor)">Colour_ShowcaseLabelLightShade</include>
        <include condition="Skin.HasSetting(darkfloor)">Colour_ShowcaseLabelNightShade</include>
        <visible>Control.IsVisible(7777)</visible>
      </control>
      <control type="label" id="72">
        <label>[UPPERCASE]$INFO[ListItem.Genre][/UPPERCASE]</label>
        <include>FloorTextDetailLabel</include>
        <visible>[Container.Content(movies) | Container.Content(episodes)] + !IsEmpty(ListItem.Genre)</visible>
      </control>
      <control type="label" id="72">
        <label>$INFO[ListItem.Album,, -] $INFO[ListItem.Artist]</label>
        <include>FloorTextDetailLabel</include>
        <visible>Container.Content(songs)</visible>
      </control>
      <control type="label" id="72">
        <label>$LOCALIZE[21898]: [COLOR d0ffffff]$INFO[ListItem.Property(Artist_YearsActive)][/COLOR]</label>
        <include>FloorTextDetailLabel</include>
        <visible>Container.Content(artists) + !IsEmpty(ListItem.Property(Artist_YearsActive))</visible>
      </control>
      <control type="label" id="72">
        <info>ListItem.Label2</info>
        <include>FloorTextDetailLabel</include>
        <visible>Window.IsActive(programs) | Container.Content(albums) | Window.IsActive(musicfiles)</visible>
      </control>
      <control type="label" id="72">
        <label>$INFO[ListItem.TVShowTitle]</label>
        <include>FloorTextDetailLabel</include>
        <visible>[Container.Content(episodes) + !IsEmpty(ListItem.Episode)] | Container.Content(seasons)</visible>
      </control>
      <control type="label" id="72">
        <info>ListItem.PictureResolution</info>
        <include>FloorTextDetailLabel</include>
        <visible>Window.IsActive(pictures) + !IsEmpty(ListItem.PictureResolution)</visible>
      </control>
      <control type="label" id="72">
        <label>[UPPERCASE]$INFO[ListItem.Episode] $LOCALIZE[31406][/UPPERCASE]</label>
        <include>FloorTextDetailLabel</include>
        <visible>Container.Content(tvshows) + !IsEmpty(ListItem.Episode)</visible>
      </control>
      <control type="label" id="73">
        <info>ListItem.year</info>
        <include>FloorTextDetailLabel2</include>
        <visible>!Control.IsVisible(7777) + [[Skin.HasSetting(showcaseinfolines) + Control.IsVisible(57)] | Control.IsVisible(53) | Control.IsVisible(55)]</visible>
        <visible>Container.Content(albums) | Window.IsActive(musicfiles)</visible>
      </control>
      <control type="label" id="73">
        <label>[UPPERCASE]$INFO[ListItem.Duration,, $LOCALIZE[12391]]$INFO[ListItem.year, - ,][/UPPERCASE]</label>
        <include>FloorTextDetailLabel2</include>
        <visible>!Control.IsVisible(7777) + Container.Content(movies) + [[Skin.HasSetting(showcaseinfolines) + Control.IsVisible(57)] | Control.IsVisible(53) | Control.IsVisible(55)]</visible>
      </control>
      <control type="label" id="73">
        <label>$LOCALIZE[21894]: [COLOR d0ffffff]$INFO[ListItem.Property(Artist_Formed)][/COLOR]</label>
        <include>FloorTextDetailLabel2</include>
        <visible>!Control.IsVisible(7777) + Container.Content(artists) + !IsEmpty(ListItem.Property(Artist_Formed)) + [[Skin.HasSetting(showcaseinfolines) + Control.IsVisible(57)] | Control.IsVisible(53) | Control.IsVisible(55)]</visible>
      </control>
    </control>
  </include>
  <include name="FloorTextLabel">
    <align>center</align>
    <aligny>center</aligny>
    <include>Animation_CommonFade</include>
    <include>Animation_HideShowcase</include>
    <include>Animation_HideMultiplex</include>
    <visible>![Control.HasFocus(60) | Control.HasFocus(66) | Control.HasFocus(68) | Control.HasFocus(70) | Control.HasFocus(70197) | Control.HasFocus(197)]</visible>
  </include>
  <include name="FloorTextMainLabel">
    <include>FloorTextLabel</include>
    <posx>315</posx>
    <posy>693</posy>
    <width>650</width>
    <font>Font_FloorTextMainLabel</font>
    <include condition="!Skin.HasSetting(darkfloor)">Colour_ShowcaseLabelLightShade</include>
    <include condition="Skin.HasSetting(darkfloor)">Colour_ShowcaseLabelNightShade</include>
    <visible>!Control.IsVisible(7777)</visible>
  </include>
  <include name="FloorTextMainLabelWide">
    <include>FloorTextLabel</include>
    <posx>200</posx>
    <posy>693</posy>
    <width>880</width>
    <font>Font_FloorTextMainLabel</font>
    <include condition="!Skin.HasSetting(darkfloor)">Colour_ShowcaseLabelLightShade</include>
    <include condition="Skin.HasSetting(darkfloor)">Colour_ShowcaseLabelNightShade</include>
    <visible>!Control.IsVisible(7777)</visible>
  </include>
  <include name="FloorTextDetailLabel">
    <include>FloorTextLabel</include>
    <posx>340</posx>
    <posy>670</posy>
    <width>600</width>
    <font>Font_FloorTextDetailLabel</font>
    <visible>!Control.IsVisible(7777) + [Skin.HasSetting(showcaseinfolines) | !Control.IsVisible(57)]</visible>
    <include condition="!Skin.HasSetting(darkfloor)">Colour_ShowcaseLabelLightShade</include>
    <include condition="Skin.HasSetting(darkfloor)">Colour_ShowcaseLabelNightShade</include>
  </include>
  <include name="FloorTextDetailLabel2">
    <include>FloorTextLabel</include>
    <posx>340</posx>
    <posy>655</posy>
    <width>600</width>
    <font>Font_FloorTextDetailLabel</font>
    <include condition="!Skin.HasSetting(darkfloor)">Colour_ShowcaseLabelLightShade</include>
    <include condition="Skin.HasSetting(darkfloor)">Colour_ShowcaseLabelNightShade</include>
  </include>
  <include name="Furniture_NowPlayingWidget">
    <control type="group">
      <include>Animation_WidgetZoom</include>
      <animation effect="slide" time="800" start="0,0" end="0,-200" tween="cubic" easing="inout" condition="[Control.IsVisible(53) + !Control.HasFocus(53) + !Control.HasFocus(71)] | [Control.IsVisible(57) + Control.HasFocus(70197)] | Control.IsVisible(7777)">Conditional</animation>
      <visible>Player.HasMedia + !Control.IsVisible(560) + !Control.IsVisible(54)</visible>
      <posx>0</posx>
      <posy>0</posy>
      <control type="image">
        <width>481</width>
        <height>32</height>
        <texture flipy="true" flipx="true">common/timepanel_mid.png</texture>
      </control>
      <control type="progress" id="20">
        <description>Progressbar</description>
        <posx>280</posx>
        <posy>2</posy>
        <width>176</width>
        <height>13</height>
        <texturebg>list/progress_back.png</texturebg>
        <lefttexture>list/progress_left.png</lefttexture>
        <midtexture>list/progress_mid.png</midtexture>
        <righttexture>list/progress_right.png</righttexture>
        <overlaytexture>-</overlaytexture>
        <info>Player.Progress</info>
      </control>
      <control type="label">
        <posx>90</posx>
        <posy>-2</posy>
        <width>180</width>
        <height>18</height>
        <font>Font_NowPlaying</font>
        <textcolor>a8FFFFFF</textcolor>
        <scroll>true</scroll>
        <label>[UPPERCASE][COLOR a8FFFFFF]$INFO[MusicPlayer.Artist][/COLOR][/UPPERCASE]</label>
      </control>
      <control type="label">
        <posx>92</posx>
        <posy>14</posy>
        <width>180</width>
        <height>18</height>
        <font>Font_NowPlaying</font>
        <textcolor>a8FFFFFF</textcolor>
        <scroll>true</scroll>
        <label>[UPPERCASE][COLOR FFFFFFFF]$INFO[MusicPlayer.Title][/COLOR][/UPPERCASE]</label>
      </control>
      <control type="label">
        <posx>92</posx>
        <posy>-2</posy>
        <width>180</width>
        <height>18</height>
        <font>Font_NowPlaying</font>
        <textcolor>a8FFFFFF</textcolor>
        <scroll>true</scroll>
        <label>[UPPERCASE][COLOR FFFFFFFF]$INFO[Videoplayer.TVShowTitle][/COLOR][/UPPERCASE]</label>
      </control>
      <control type="label">
        <posx>92</posx>
        <posy>6</posy>
        <width>180</width>
        <height>18</height>
        <font>Font_NowPlaying</font>
        <textcolor>a8FFFFFF</textcolor>
        <scroll>true</scroll>
        <label>[UPPERCASE][COLOR FFFFFFFF]$INFO[Videoplayer.Title][/COLOR][/UPPERCASE]</label>
        <animation effect="slide" start="0,0" end="0,7" time="0" condition="VideoPlayer.Content(episodes)">Conditional</animation>
      </control>
      <control type="label">
        <description>Current time</description>
        <posx>260</posx>
        <posy>14</posy>
        <width>200</width>
        <height>20</height>
        <font>Font_NowPlaying</font>
        <label>$INFO[MusicPlayer.Time] / $INFO[MusicPlayer.Duration]</label>
        <align>center</align>
      </control>
      <control type="image">
        <description>Cd overlay</description>
        <animation effect="rotate" end="-360" center="auto" time="5000" loop="true" reversible="false" condition="!Player.Paused">Conditional</animation>
        <animation effect="fade" time="100">Hidden</animation>
        <aspectratio>keep</aspectratio>
        <width>54</width>
        <height>54</height>
        <posx>22</posx>
        <posy>5</posy>
        <fadetime>300</fadetime>
        <texture fallback="cdart/default.png">$INFO[Player.FolderPath]cdart.png</texture>
        <aspectratio align="bottom">keep</aspectratio>
      </control>
      <control type="image">
        <description>COVER</description>
        <aspectratio>stretch</aspectratio>
        <width>60</width>
        <height>60</height>
        <posx>4</posx>
        <posy>2</posy>
        <visible>Player.HasAudio + !Control.IsVisible(560) + !Control.IsVisible(54)</visible>
        <animation effect="fade" time="800">Hidden</animation>
        <texture fallback="DefaultAlbumCover.png" diffuse="thumbs/cdcover_mask2.png">$INFO[MusicPlayer.Cover]</texture>
      </control>
      <control type="image">
        <description>COVER</description>
        <aspectratio scalediffuse="false">scale</aspectratio>
        <width>50</width>
        <height>75</height>
        <posx>4</posx>
        <posy>2</posy>
        <visible>Player.HasVideo + !Control.IsVisible(560) + !Control.IsVisible(54)</visible>
        <animation effect="fade" time="800">Hidden</animation>
        <texture fallback="DefaultVideo.png" diffuse="thumbs/cdcover_mask2.png">$INFO[VideoPlayer.Cover]</texture>
      </control>
    </control>
  </include>
  <include name="Furniture_DarkGradient">
    <control type="image">
      <posx>0</posx>
      <posy>675</posy>
      <width>1280</width>
      <height>48</height>
      <texture>showcase/showcase_gradient.png</texture>
      <visible>Skin.HasSetting(darkfloor) + [Control.IsVisible(57) | Control.IsVisible(52) | Control.IsVisible(552)]</visible>
      <include>Animation_CommonFade</include>
    </control>
  </include>
  <!-- Settings windows -->
  <include name="Furniture_SettingsBackPanel">
    <control type="image">
      <description>background image</description>
      <posx>23</posx>
      <posy>23</posy>
      <width>1233</width>
      <height>673</height>
      <texture>settings/settings_panelback.png</texture>
    </control>
    <control type="multiimage">
      <posx>38</posx>
      <posy>26</posy>
      <width>1200</width>
      <height>653</height>
      <include>BackgroundEffectCommon</include>
    </control>
  </include>
  <include name="Furniture_SettingsFrontPanel">
    <control type="image">
      <description>Front pane for Settings panel</description>
      <posx>42</posx>
      <posy>28</posy>
      <width>1196</width>
      <height>651</height>
      <texture>settings/settings_panelfront.png</texture>
    </control>
  </include>
  <include name="Furniture_SettingsTutorialSlide">
    <animation effect="fade" time="500">Visible</animation>
    <animation effect="fade" time="200">Hidden</animation>
    <animation effect="fade" time="500">WindowOpen</animation>
    <animation effect="fade" time="200">WindowClose</animation>
    <width>840</width>
    <height>472</height>
    <timeperimage>999999</timeperimage>
    <fadetime>300</fadetime>
    <randomize>true</randomize>
  </include>
  <include name="Furniture_Debug">
    <control type="label">
      <posx>20</posx>
      <posy>150</posy>
      <width>1000</width>
      <font>Font_Debug</font>
      <label>$INFO[Window.Property(xmlfile)] / $INFO[System.Screenresolution] / $LOCALIZE[158] - $INFO[System.FreeMemory] [CR] $INFO[System.CurrentWindow] $INFO[System.CurrentControl][CR]$LOCALIZE[31603] $INFO[System.FPS][CR]$LOCALIZE[31604][CR]$INFO[System.InternetState][CR]$LOCALIZE[31606] $INFO[Container.Viewmode]</label>
      <visible>Skin.HasSetting(debug) + !Skin.HasSetting(debuginfo)</visible>
    </control>
  </include>
  <include name="Furniture_DebugGrid">
    <control type="image">
      <include>Dimensions_Fullscreen</include>
      <texture>DebugGrid.png</texture>
      <visible>!Skin.HasSetting(debuginfo)</visible>
    </control>
  </include>
  <include name="FilemanagerPanelExtents">
    <width>620</width>
    <height>647</height>
  </include>
  <include name="FilemanagerPanelCommonObjects">
    <control type="image">
      <include>FilemanagerPanelExtents</include>
      <posx>0</posx>
      <posy>0</posy>
      <texture>list/listpanel_black.png</texture>
    </control>
    <control type="image">
      <include>FilemanagerPanelExtents</include>
      <posx>0</posx>
      <posy>0</posy>
      <texture>list/listpanel_back_noreflect.png</texture>
    </control>
    <control type="image">
      <posx>525</posx>
      <posy>64</posy>
      <width>85</width>
      <height>555</height>
      <texture>list/listpanel_detailwide.png</texture>
    </control>
  </include>
  <include name="ListLabel_Main_Playlist">
    <posx>70</posx>
    <posy>0</posy>
    <width>430</width>
    <height>41</height>
    <font>Font_List</font>
    <aligny>center</aligny>
  </include>
  <include name="BackgroundEffectCommon">
    <animations effect="fade" time="1000">Visible</animations>
    <animations effect="fade" time="1000">Hidden</animations>
    <imagepath>cerberus</imagepath>
    <timeperimage>0</timeperimage>
    <fadetime>0</fadetime>
    <loop>yes</loop>
    <randomize>false</randomize>
    <visible>!Skin.HasSetting(backgroundeffectoff)</visible>
  </include>
  <include name="BackgroundEffect">
    <control type="multiimage">
      <include>Animation_OpenCloseZoom</include>
      <posx>0</posx>
      <posy>0</posy>
      <width>1280</width>
      <height>720</height>
      <include>BackgroundEffectCommon</include>
    </control>
  </include>
  <include name="BlackOverlayCommon">
    <posx>0</posx>
    <posy>-60</posy>
    <width>1280</width>
    <height>662</height>
    <texture>common/black.png</texture>
    <colordiffuse>AAFFFFFF</colordiffuse>
    <animation effect="fade" end="100" time="600" reversible="false">Visible</animation>
    <animation effect="fade" end="0" time="500" reversible="false">Hidden</animation>
  </include>
  <include name="VideoInfoScreen">
    <include>Object_AlaskaPausedLabel</include>
    <control type="group">
      <posx>0</posx>
      <posy>600</posy>
      <width>1280</width>
      <height>159</height>
      <animation type="Visible">
        <effect type="fade" time="400" start="0" end="100"/>
        <effect type="slide" time="400" start="0,159" end="0,0" easing="out" tween="cubic"/>
      </animation>
      <animation type="Hidden">
        <effect type="fade" time="400" start="100" end="0"/>
        <effect type="slide" time="400" start="0,0" end="0,159" easing="in" tween="cubic"/>
      </animation>
      <animation type="WindowOpen">
        <effect type="fade" time="400" start="0" end="100"/>
        <effect type="slide" time="400" start="0,159" end="0,0" easing="out" tween="cubic"/>
      </animation>
      <animation type="WindowClose">
        <effect type="fade" time="400" start="100" end="0"/>
        <effect type="slide" time="400" start="0,0" end="0,159" easing="in" tween="cubic"/>
      </animation>
      <include>Animation_CommonFade</include>
      <control type="image">
        <description>Panel</description>
        <posx>0</posx>
        <posy>0</posy>
        <height>159</height>
        <width>1280</width>
        <colordiffuse>ffffffff</colordiffuse>
        <texture>osd/osd_back.png</texture>
      </control>
      <control type="multiimage">
        <posx>0</posx>
        <posy>0</posy>
        <width>1280</width>
        <height>159</height>
        <include>BackgroundEffectCommon</include>
      </control>
      <control type="progress" id="23">
        <description>Progressbar</description>
        <posx>260</posx>
        <posy>60</posy>
        <width>760</width>
        <height>15</height>
        <info>Player.Progress</info>
        <texturebg>osd/osd_progress_back.png</texturebg>
        <lefttexture>osd/osd_progress_left.png</lefttexture>
        <midtexture>osd/osd_progress_mid.png</midtexture>
        <righttexture>osd/osd_progress_right.png</righttexture>
        <overlaytexture>-</overlaytexture>
        <visible>true</visible>
      </control>
      <control type="group">
        <control type="label">
          <posx>1260</posx>
          <posy>-40</posy>
          <width>1280</width>
          <height>15</height>
          <align>right</align>
          <aligny>center</aligny>
          <font>Sml_Text</font>
          <label>$LOCALIZE[31706] 2X</label>
          <textcolor>33FFFFFF</textcolor>
          <visible>Player.Forwarding2x</visible>
        </control>
	<control type="label">
	  <posx>1260</posx>
	  <posy>-40</posy>
	  <width>1280</width>
	  <height>15</height>
	  <align>right</align>
	  <aligny>center</aligny>
	  <font>Sml_Text</font>
	  <label>$LOCALIZE[31706] 4X</label>
	  <textcolor>33FFFFFF</textcolor>
	  <visible>Player.Forwarding4x</visible>
	</control>
        <control type="label">
          <posx>1260</posx>
          <posy>-40</posy>
          <width>1280</width>
          <height>15</height>
          <align>right</align>
          <aligny>center</aligny>
          <font>Sml_Text</font>
          <label>$LOCALIZE[31706] 8X</label>
          <textcolor>33FFFFFF</textcolor>
          <visible>Player.Forwarding8x</visible>
        </control>
        <control type="label">
          <posx>1260</posx>
          <posy>-40</posy>
          <width>1280</width>
          <height>15</height>
          <align>right</align>
          <aligny>center</aligny>
          <font>Sml_Text</font>
          <label>$LOCALIZE[31706] 16X</label>
          <textcolor>33FFFFFF</textcolor>
          <visible>Player.Forwarding16x</visible>
        </control>
        <control type="label">
          <posx>1260</posx>
          <posy>-40</posy>
          <width>1280</width>
          <height>15</height>
          <align>right</align>
          <aligny>center</aligny>
          <font>Sml_Text</font>
          <textcolor>33FFFFFF</textcolor>
          <label>$LOCALIZE[31706] 32X</label>
          <textcolor>22FFFFFF</textcolor>
          <visible>Player.Forwarding32x</visible>
        </control>
        <control type="label">
          <posx>1260</posx>
          <posy>-40</posy>
          <width>1280</width>
          <height>15</height>
          <align>right</align>
          <aligny>center</aligny>
          <font>Sml_Text</font>
          <textcolor>33FFFFFF</textcolor>
          <label>$LOCALIZE[31705] 2X</label>
          <visible>Player.Rewinding2x</visible>
        </control>
        <control type="label">
          <posx>1260</posx>
          <posy>-40</posy>
          <width>1280</width>
          <height>15</height>
          <align>right</align>
          <aligny>center</aligny>
          <font>Sml_Text</font>
          <textcolor>33FFFFFF</textcolor>
          <include>Objects_OSDSeekReverse</include>
          <label>$LOCALIZE[31705] 4X</label>
          <visible>Player.Rewinding4x</visible>
        </control>
        <control type="label">
          <posx>1260</posx>
          <posy>-40</posy>
          <width>1280</width>
          <height>15</height>
          <align>right</align>
          <aligny>center</aligny>
          <font>Sml_Text</font>
          <textcolor>33FFFFFF</textcolor>
          <include>Objects_OSDSeekReverse</include>
          <label>$LOCALIZE[31705] 8X</label>
          <visible>Player.Rewinding8x</visible>
        </control>
        <control type="label">
          <posx>1260</posx>
          <posy>-40</posy>
          <width>1280</width>
          <height>15</height>
          <align>right</align>
          <aligny>center</aligny>
          <font>Sml_Text</font>
          <textcolor>33FFFFFF</textcolor>
          <include>Objects_OSDSeekReverse</include>
          <label>$LOCALIZE[31705] 16X</label>
          <visible>Player.Rewinding16x</visible>
        </control>
        <control type="label">
          <posx>1260</posx>
          <posy>-40</posy>
          <width>1280</width>
          <height>15</height>
          <align>right</align>
          <aligny>center</aligny>
          <font>Sml_Text</font>
          <textcolor>33FFFFFF</textcolor>
          <include>Objects_OSDSeekReverse</include>
          <label>$LOCALIZE[31705] 32X</label>
          <visible>Player.Rewinding32x</visible>
        </control>
      </control>

      <!-- Times -->
      <control type="label">
        <posx>260</posx>
        <posy>30</posy>
        <width>760</width>
	<height>25</height>
        <font>Font_OSDTime</font>
        <colordiffuse>d0FFFFFF</colordiffuse>
	<align>left</align>
        <label>$INFO[VideoPlayer.Time]</label>
      </control>
      <control type="label">
        <posx>260</posx>
        <posy>85</posy>
        <width>760</width>
        <height>25</height>
        <font>Font_OSDTime</font>
	<align>left</align>
	<textcolor>60FFFFFF</textcolor>
        <label>$LOCALIZE[31720]: [COLOR d0ffffff]$INFO[System.Time][/COLOR]</label>
      </control>
      <control type="label">
        <posx>1020</posx>
        <posy>30</posy>
        <width>760</width>
        <height>25</height>
        <font>Font_OSDTime</font>
	<align>right</align>
        <label>$INFO[VideoPlayer.Duration]</label>
      </control>
      <control type="label">
        <posx>1020</posx>
        <posy>85</posy>
        <width>760</width>
        <height>25</height>
	<font>Font_OSDTime</font>
	<textcolor>60FFFFFF</textcolor>
	<align>right</align>
        <label>$LOCALIZE[31710]: [COLOR d0ffffff]$INFO[Player.FinishTime][/COLOR]</label>
      </control>

      <control type="label">
        <posx>340</posx>
        <posy>22</posy>
        <width>610</width>
        <height>25</height>
        <align>center</align>
        <aligny>center</aligny>
        <font>Font_OSDMusicTitle</font>
        <label>$INFO[VideoPlayer.Title]</label>
        <visible>VideoPlayer.Content(movies) | VideoPlayer.Content(episodes)</visible>
        <scroll>true</scroll>
      </control>

      <!-- center -->
      <control type="group">
        <visible>VideoPlayer.Content(episodes)</visible>
        <control type="label">
          <posx>430</posx>
          <posy>78</posy>
          <width>420</width>
          <height>15</height>
          <align>center</align>
          <aligny>center</aligny>
          <font>Font_OSDGenre</font>
          <label>$INFO[VideoPlayer.Season,$LOCALIZE[31062] , - ]$INFO[VideoPlayer.Episode,$LOCALIZE[31063] ,]</label>
        </control>
        <control type="fadelabel">
	  <posx>430</posx>
	  <posy>95</posy>
	  <width>420</width>
	  <height>15</height>
	  <align>center</align>
	  <aligny>center</aligny>
	  <font>Font_OSDGenre</font>
	  <label>$INFO[VideoPlayer.Studio,$LOCALIZE[31404] ,]</label>
	  <label>$INFO[VideoPlayer.premiered,$LOCALIZE[20416]: ,]</label>
	  <scrollout>false</scrollout>
	  <scrollspeed>200</scrollspeed>
	  <pauseatend>3000</pauseatend>
	</control>
      </control>
      <control type="group">
        <visible>VideoPlayer.Content(movies)</visible>
        <control type="label">
          <posx>430</posx>
          <posy>78</posy>
          <width>420</width>
          <height>15</height>
          <align>center</align>
          <aligny>center</aligny>
          <font>Font_OSDGenre</font>
          <label>$INFO[VideoPlayer.Genre]</label>
        </control>
        <control type="fadelabel">
          <posx>430</posx>
          <posy>95</posy>
          <width>420</width>
          <height>15</height>
          <align>center</align>
          <aligny>center</aligny>
          <font>Font_OSDGenre</font>
          <label>$INFO[VideoPlayer.Director,$LOCALIZE[31402]: ,]</label>
          <label>$INFO[VideoPlayer.Writer,$LOCALIZE[31401]: ,]</label>
          <scrollout>false</scrollout>
          <scrollspeed>100</scrollspeed>
          <pauseatend>3000</pauseatend>
        </control>
      </control>


      <!-- left column -->
      <control type="group">
        <posx>0</posx>
        <posy>0</posy>
        <control type="group">
          <visible>VideoPlayer.Content(episodes)</visible>
          <control type="image" id="1000">
            <description>Clearart</description>
            <posx>15</posx>
            <posy>-19</posy>
            <width>230</width>
            <height>156</height>
            <texture background="true">$INFO[Player.FolderPath]/clearart.png</texture>
            <aspectratio>keep</aspectratio>
            <animation type="WindowOpen">
              <effect type="slide" start="-300,0" end="0,0" time="600" tween="cubic" easing="out"/>
              <effect type="fade" start="0" end="100" time="600"/>
            </animation>
            <animation type="WindowClose">
              <effect type="slide" start="0,0" end="-300,0" time="600" tween="cubic" easing="out"/>
              <effect type="fade" start="100" end="0" time="600"/>
            </animation>
          </control>
          <control type="image" id="1001">
            <description>Clearart</description>
            <posx>15</posx>
            <posy>-19</posy>
            <width>230</width>
            <height>156</height>
            <texture background="true">$INFO[Player.FolderPath]/../clearart.png</texture>
            <aspectratio>keep</aspectratio>
            <visible>IsEmpty(Control.GetLabel(1000))</visible>
            <animation type="WindowOpen">
              <effect type="slide" start="-300,0" end="0,0" time="600" tween="cubic" easing="out"/>
              <effect type="fade" start="0" end="100" time="600"/>
            </animation>
            <animation type="WindowClose">
              <effect type="slide" start="0,0" end="-300,0" time="600" tween="cubic" easing="out"/>
              <effect type="fade" start="100" end="0" time="600"/>
            </animation>
          </control>
          <control type="image" id="1002">
            <description>Logo.png fallback</description>
            <posx>15</posx>
            <posy>-29</posy>
            <width>230</width>
            <height>156</height>
            <texture background="true">$INFO[Player.FolderPath]/../logo.png</texture>
            <aspectratio>keep</aspectratio>
            <visible>IsEmpty(Control.GetLabel(1000)) + IsEmpty(Control.GetLabel(1001))</visible>
            <animation type="WindowOpen">
              <effect type="slide" start="-300,0" end="0,0" time="600" tween="cubic" easing="out"/>
              <effect type="fade" start="0" end="100" time="600"/>
            </animation>
            <animation type="WindowClose">
              <effect type="slide" start="0,0" end="-300,0" time="600" tween="cubic" easing="out"/>
              <effect type="fade" start="100" end="0" time="600"/>
            </animation>
          </control>
          <control type="image" id="1003">
            <description>Logo.png fallback</description>
            <posx>15</posx>
            <posy>-29</posy>
            <width>230</width>
            <height>156</height>
            <visible>IsEmpty(Control.GetLabel(1000)) + IsEmpty(Control.GetLabel(1001)) + IsEmpty(Control.GetLabel(1002))</visible>
            <texture background="true">$INFO[Player.FolderPath]/../logo.png</texture>
            <aspectratio>keep</aspectratio>
            <animation type="WindowOpen">
              <effect type="slide" start="-300,0" end="0,0" time="600" tween="cubic" easing="out"/>
              <effect type="fade" start="0" end="100" time="600"/>
            </animation>
            <animation type="WindowClose">
              <effect type="slide" start="0,0" end="-300,0" time="600" tween="cubic" easing="out"/>
              <effect type="fade" start="100" end="0" time="600"/>
            </animation>
          </control>
        </control>
        <control type="group">
          <visible>VideoPlayer.Content(movies)</visible>
          <control type="image">
            <description>IMDB Rating</description>
            <posx>65</posx>
            <posy>70</posy>
            <width>120</width>
            <height>24</height>
            <texture>$INFO[VideoPlayer.Rating,flags/starrating/,.png]</texture>
          </control>
          <control type="label">
            <posx>65</posx>
            <posy>37</posy>
            <width>130</width>
            <height>25</height>
            <align>center</align>
            <aligny>center</aligny>
            <font>Font_OSDMusicTitle</font>
            <label>$INFO[VideoPlayer.Year]</label>
          </control>
        </control>
      </control>
      <!-- right column -->
      <control type="image">
        <visible>!VideoPlayer.Content(episodes) + !VideoPlayer.Content(musicvideos)</visible>
        <description>Cover Image</description>
        <posx>1050</posx>
        <posy>-200</posy>
        <width>200</width>
        <height>310</height>
        <texture diffuse="thumbs/movieposter_mask.png">$INFO[VideoPlayer.Cover]</texture>
        <bordertexture border="-21">thumbs/poster_shadow.png</bordertexture>
        <aspectratio aligny="bottom">Keep</aspectratio>
        <animation type="WindowOpen">
          <effect type="slide" start="300,0" end="0,0" time="600" tween="cubic" easing="out"/>
        </animation>
        <animation type="WindowClose">
          <effect type="slide" start="0,0" end="300,0" time="600" tween="cubic" easing="out"/>
          <effect type="fade" start="100" end="0" time="600"/>
        </animation>
      </control>
      <control type="image">
        <visible>VideoPlayer.Content(episodes) | VideoPlayer.Content(musicvideos)</visible>
        <description>Cover Image</description>
        <posx>1045</posx>
        <posy>-40</posy>
        <width>210</width>
        <height>144</height>
        <texture diffuse="thumbs/multiplex_tvmask.png" background="true">$INFO[VideoPlayer.Cover]</texture>
        <aspectratio scalediffuse="false">scale</aspectratio>
        <bordertexture border="-26">thumbs/episode_poster_shadow.png</bordertexture>
        <animation type="WindowOpen">
          <effect type="slide" start="300,0" end="0,0" time="600" tween="cubic" easing="out"/>
        </animation>
        <animation type="WindowClose">
          <effect type="slide" start="0,0" end="300,0" time="600" tween="cubic" easing="out"/>
          <effect type="fade" start="100" end="0" time="600"/>
        </animation>
      </control>
      <control type="image">
        <description>Pause button</description>
        <posx>920</posx>
        <posy>-30</posy>
        <width>73</width>
        <height>72</height>
        <texture background="true">osd/paused_mod.png</texture>
        <aspectratio>keep</aspectratio>
        <visible>Player.Paused + !Skin.HasSetting(AlaskaPausedLabel)</visible>
        <animation type="WindowOpen">
          <effect type="slide" start="-300,0" end="0,0" time="600" tween="cubic" easing="out"/>
          <effect type="fade" start="0" end="100" time="600"/>
        </animation>
        <animation type="WindowClose">
          <effect type="slide" start="0,0" end="-300,0" time="600" tween="cubic" easing="out"/>
          <effect type="fade" start="100" end="0" time="600"/>
        </animation>
        <animation type="Visible">
          <effect type="slide" start="-300,0" end="0,0" time="600" tween="cubic" easing="out"/>
          <effect type="fade" start="0" end="100" time="600"/>
        </animation>
        <animation type="Hidden">
          <effect type="slide" start="0,0" end="-300,0" time="600" tween="cubic" easing="out"/>
          <effect type="fade" start="100" end="0" time="600"/>
        </animation>
      </control>
    </control>
  </include>
</includes>
